trytond/modules/twilio_messages/__init__.py
trytond/modules/twilio_messages/routes.py
trytond/modules/twilio_messages/tryton.cfg
trytond/modules/twilio_messages/twilio_messages.py
trytond/modules/twilio_messages/twilio_messages.xml
trytond/modules/twilio_messages/tests/__init__.py
trytond/modules/twilio_messages/tests/scenario_twilio_messages.rst
trytond/modules/twilio_messages/tests/test_twilio_messages.py
trytond/modules/twilio_messages/view/message_form.xml
trytond/modules/twilio_messages/view/message_list.xml
trytond/modules/twilio_messages/view/send_message_view_form.xml
trytonlls_twilio_messages-4.4.0.dist-info/METADATA
trytonlls_twilio_messages-4.4.0.dist-info/RECORD
trytonlls_twilio_messages-4.4.0.dist-info/WHEEL
trytonlls_twilio_messages-4.4.0.dist-info/entry_points.txt
trytonlls_twilio_messages-4.4.0.dist-info/top_level.txt
